velrecover/__init__.py
velrecover/__main__.py
velrecover/core/__init__.py
velrecover/core/base.py
velrecover/core/gauss_blur.py
velrecover/core/linear_models.py
velrecover/core/logarithmic_models.py
velrecover/core/rbf_models.py
velrecover/core/two_step.py
velrecover/examples/README.txt
velrecover/examples/SEGY/RIV6.segy
velrecover/examples/VELS/RAW/RIV6_vnmo.dat
velrecover/ui/_0_welcome_tab.py
velrecover/ui/_1_load_data_tab.py
velrecover/ui/_2_edit_tab.py
velrecover/ui/_3_interpolate_tab.py
velrecover/ui/_4_save_tab.py
velrecover/ui/__init__.py
velrecover/ui/help_dialogs.py
velrecover/ui/main_window.py
velrecover/ui/navigation_panel.py
velrecover/ui/tab_container.py
velrecover/ui/theme.qss
velrecover/utils/__init__.py
velrecover/utils/console_utils.py
velrecover/utils/resource_utils.py
velrecover/utils/velocity_distribution.py
velrecover/utils/velocity_export.py
velrecover/utils/visualization_utils.py
velrecover-1.0.1.dist-info/licenses/LICENSE
velrecover-1.0.1.dist-info/METADATA
velrecover-1.0.1.dist-info/WHEEL
velrecover-1.0.1.dist-info/entry_points.txt
velrecover-1.0.1.dist-info/top_level.txt
velrecover-1.0.1.dist-info/RECORD
